tests/__init__.py
tests/mock_sshclient.py
tests/test_arguments.py
tests/test_login.py
tests/test_prometheus.py
tests/test_scrape.py
tests/test_server.py
zyxelprometheus/__init__.py
zyxelprometheus/arguments.py
zyxelprometheus/exceptions.py
zyxelprometheus/login.py
zyxelprometheus/prometheus.py
zyxelprometheus/scrape.py
zyxelprometheus/server.py
zyxelprometheus-0.5.5.data/scripts/zyxelprometheus
zyxelprometheus-0.5.5.dist-info/LICENSE
zyxelprometheus-0.5.5.dist-info/METADATA
zyxelprometheus-0.5.5.dist-info/WHEEL
zyxelprometheus-0.5.5.dist-info/top_level.txt
zyxelprometheus-0.5.5.dist-info/RECORD
