Metadata-Version: 2.1
Name: zyxelprometheus
Version: 0.5.5
Summary: Get statistics from a Zyxel router and expose them to Prometheus.
Home-page: https://github.com/andrewjw/zyxelprometheus
Author: Andrew Wilkinson
Author-email: andrewjwilkinson@gmail.com
License: UNKNOWN
Platform: UNKNOWN
Classifier: Programming Language :: Python :: 3.8
Classifier: License :: OSI Approved :: GNU General Public License v3 (GPLv3)
Classifier: Operating System :: OS Independent
Requires-Python: >=3.8
Requires-Dist: coverage (==4.5.4)
Requires-Dist: paramiko (==2.7.2)
Requires-Dist: pycodestyle (==2.6.0)
Requires-Dist: python-coveralls (==2.9.3)
Requires-Dist: python-semantic-release (==7.13.2)
